razator_utils/log.py
razator_utils/__init__.py
razator_utils/razator_utils.py
razator_utils-0.2.0.dist-info/RECORD
razator_utils-0.2.0.dist-info/top_level.txt
razator_utils-0.2.0.dist-info/METADATA
razator_utils-0.2.0.dist-info/WHEEL
razator_utils-0.2.0.dist-info/DESCRIPTION.rst
razator_utils-0.2.0.dist-info/metadata.json
