Metadata-Version: 2.0
Name: razator-utils
Version: 0.2.0
Summary: A pypi package for personal use. Containing common functions I use.
Home-page: https://github.com/razator73/razator_utils
Author: Ryan Scott
Author-email: ryan.t.scott73@gmail.com
License: GNU General Public License v3
Keywords: razator_utils
Classifier: Development Status :: 2 - Pre-Alpha
Classifier: Intended Audience :: Developers
Classifier: License :: OSI Approved :: GNU General Public License v3 (GPLv3)
Classifier: Natural Language :: English
Classifier: Programming Language :: Python :: 3
Classifier: Programming Language :: Python :: 3.6
Classifier: Programming Language :: Python :: 3.7
Classifier: Programming Language :: Python :: 3.8
Classifier: Programming Language :: Python :: 3.9
Classifier: Programming Language :: Python :: 3.10
Requires-Python: >=3.6
License-File: LICENSE
License-File: AUTHORS.rst
